eones/__init__.py
eones/constants.py
eones/errors.py
eones/formats.py
eones/humanize.py
eones/interface.py
eones/core/__init__.py
eones/core/date.py
eones/core/delta.py
eones/core/delta_calendar.py
eones/core/delta_duration.py
eones/core/parser.py
eones/core/range.py
eones/integrations/__init__.py
eones/integrations/django.py
eones/integrations/serializers.py
eones/integrations/sqlalchemy.py
eones/locales/__init__.py
eones/locales/en.py
eones/locales/es.py
eones-1.4.2.dist-info/licenses/LICENSE.md
eones-1.4.2.dist-info/METADATA
eones-1.4.2.dist-info/WHEEL
eones-1.4.2.dist-info/top_level.txt
eones-1.4.2.dist-info/RECORD
