Metadata-Version: 2.4
Name: Eones
Version: 1.4.2
Summary: Elegant time manipulation and reasoning library
Author-email: Rodrigo Ezequiel Roldán <roldriel@gmail.com>
License: # MIT License
Project-URL: repository, https://github.com/roldriel/eones
Project-URL: documentation, https://roldriel.github.io/eones/
Project-URL: Bug Tracker, https://github.com/roldriel/eones/issues
Keywords: datetime,time,calendar,library,dates,timezones
Classifier: Development Status :: 4 - Beta
Classifier: Intended Audience :: Developers
Classifier: Operating System :: OS Independent
Classifier: Programming Language :: Python
Classifier: Programming Language :: Python :: 3
Classifier: Programming Language :: Python :: 3.9
Classifier: Programming Language :: Python :: 3.10
Classifier: Programming Language :: Python :: 3.11
Classifier: Programming Language :: Python :: 3.12
Classifier: Topic :: Software Development :: Libraries :: Python Modules
Requires-Python: >=3.9
License-File: LICENSE.md
Requires-Dist: tzdata
Provides-Extra: docs
Requires-Dist: sphinx; extra == "docs"
Requires-Dist: myst-parser; extra == "docs"
Provides-Extra: test
Requires-Dist: pytest; extra == "test"
Requires-Dist: coverage; extra == "test"
Dynamic: license-file
